Project1/primeExtension/primeExtension.vhd
-- Copyright (C) 1991-2013 Altera Corporation
-- Your use of Altera Corporation's design tools, logic functions 
-- and other software and tools, and its AMPP partner logic 
-- functions, and any output files from any of the foregoing 
-- (including device programming or simulation files), and any 
-- associated documentation or information are expressly subject 
-- to the terms and conditions of the Altera Program License 
-- Subscription Agreement, Altera MegaCore Function License 
-- Agreement, or other applicable license agreement, including, 
-- without limitation, that your use is for the sole purpose of 
-- programming logic devices manufactured by Altera and sold by 
-- Altera or its authorized distributors.  Please refer to the 
-- applicable agreement for further details.

-- PROGRAM		"Quartus II 32-bit"
-- VERSION		"Version 13.1.0 Build 162 10/23/2013 SJ Web Edition"
-- CREATED		"Wed Feb 26 19:52:58 2025"

LIBRARY ieee;
USE ieee.std_logic_1164.all; 

LIBRARY work;

ENTITY primeExtension IS 
	PORT
	(
		A :  IN  STD_LOGIC;
		B :  IN  STD_LOGIC;
		C :  IN  STD_LOGIC;
		D :  IN  STD_LOGIC;
		E :  IN  STD_LOGIC;
		F :  IN  STD_LOGIC;
		O :  OUT  STD_LOGIC
	);
END primeExtension;

ARCHITECTURE bdf_type OF primeExtension IS 

SIGNAL	SYNTHESIZED_WIRE_56 :  STD_LOGIC;
SIGNAL	SYNTHESIZED_WIRE_57 :  STD_LOGIC;
SIGNAL	SYNTHESIZED_WIRE_2 :  STD_LOGIC;
SIGNAL	SYNTHESIZED_WIRE_3 :  STD_LOGIC;
SIGNAL	SYNTHESIZED_WIRE_58 :  STD_LOGIC;
SIGNAL	SYNTHESIZED_WIRE_5 :  STD_LOGIC;
SIGNAL	SYNTHESIZED_WIRE_6 :  STD_LOGIC;
SIGNAL	SYNTHESIZED_WIRE_8 :  STD_LOGIC;
SIGNAL	SYNTHESIZED_WIRE_9 :  STD_LOGIC;
SIGNAL	SYNTHESIZED_WIRE_10 :  STD_LOGIC;
SIGNAL	SYNTHESIZED_WIRE_11 :  STD_LOGIC;
SIGNAL	SYNTHESIZED_WIRE_59 :  STD_LOGIC;
SIGNAL	SYNTHESIZED_WIRE_14 :  STD_LOGIC;
SIGNAL	SYNTHESIZED_WIRE_15 :  STD_LOGIC;
SIGNAL	SYNTHESIZED_WIRE_16 :  STD_LOGIC;
SIGNAL	SYNTHESIZED_WIRE_17 :  STD_LOGIC;
SIGNAL	SYNTHESIZED_WIRE_18 :  STD_LOGIC;
SIGNAL	SYNTHESIZED_WIRE_22 :  STD_LOGIC;
SIGNAL	SYNTHESIZED_WIRE_23 :  STD_LOGIC;
SIGNAL	SYNTHESIZED_WIRE_28 :  STD_LOGIC;
SIGNAL	SYNTHESIZED_WIRE_29 :  STD_LOGIC;
SIGNAL	SYNTHESIZED_WIRE_33 :  STD_LOGIC;
SIGNAL	SYNTHESIZED_WIRE_34 :  STD_LOGIC;
SIGNAL	SYNTHESIZED_WIRE_60 :  STD_LOGIC;
SIGNAL	SYNTHESIZED_WIRE_38 :  STD_LOGIC;
SIGNAL	SYNTHESIZED_WIRE_39 :  STD_LOGIC;
SIGNAL	SYNTHESIZED_WIRE_41 :  STD_LOGIC;
SIGNAL	SYNTHESIZED_WIRE_42 :  STD_LOGIC;
SIGNAL	SYNTHESIZED_WIRE_43 :  STD_LOGIC;
SIGNAL	SYNTHESIZED_WIRE_44 :  STD_LOGIC;
SIGNAL	SYNTHESIZED_WIRE_45 :  STD_LOGIC;
SIGNAL	SYNTHESIZED_WIRE_46 :  STD_LOGIC;
SIGNAL	SYNTHESIZED_WIRE_47 :  STD_LOGIC;
SIGNAL	SYNTHESIZED_WIRE_48 :  STD_LOGIC;
SIGNAL	SYNTHESIZED_WIRE_50 :  STD_LOGIC;
SIGNAL	SYNTHESIZED_WIRE_51 :  STD_LOGIC;
SIGNAL	SYNTHESIZED_WIRE_53 :  STD_LOGIC;
SIGNAL	SYNTHESIZED_WIRE_54 :  STD_LOGIC;


BEGIN 



SYNTHESIZED_WIRE_41 <= SYNTHESIZED_WIRE_56 AND SYNTHESIZED_WIRE_57 AND E AND F;


SYNTHESIZED_WIRE_14 <= SYNTHESIZED_WIRE_2 AND SYNTHESIZED_WIRE_3;


SYNTHESIZED_WIRE_5 <= A AND C AND SYNTHESIZED_WIRE_58;


SYNTHESIZED_WIRE_6 <= E AND F;


SYNTHESIZED_WIRE_15 <= SYNTHESIZED_WIRE_5 AND SYNTHESIZED_WIRE_6;


SYNTHESIZED_WIRE_10 <= SYNTHESIZED_WIRE_56 AND B AND D;


SYNTHESIZED_WIRE_11 <= E AND F;


O <= SYNTHESIZED_WIRE_8 OR SYNTHESIZED_WIRE_9;


SYNTHESIZED_WIRE_45 <= SYNTHESIZED_WIRE_10 AND SYNTHESIZED_WIRE_11;


SYNTHESIZED_WIRE_17 <= A AND SYNTHESIZED_WIRE_59 AND C;


SYNTHESIZED_WIRE_18 <= SYNTHESIZED_WIRE_58 AND F;


SYNTHESIZED_WIRE_8 <= SYNTHESIZED_WIRE_14 OR SYNTHESIZED_WIRE_15 OR SYNTHESIZED_WIRE_16;


SYNTHESIZED_WIRE_16 <= SYNTHESIZED_WIRE_17 AND SYNTHESIZED_WIRE_18;


SYNTHESIZED_WIRE_22 <= SYNTHESIZED_WIRE_56 AND B AND SYNTHESIZED_WIRE_57;


SYNTHESIZED_WIRE_23 <= SYNTHESIZED_WIRE_58 AND F;


SYNTHESIZED_WIRE_46 <= SYNTHESIZED_WIRE_22 AND SYNTHESIZED_WIRE_23;


SYNTHESIZED_WIRE_28 <= SYNTHESIZED_WIRE_56 AND SYNTHESIZED_WIRE_59 AND SYNTHESIZED_WIRE_57;


SYNTHESIZED_WIRE_29 <= SYNTHESIZED_WIRE_58 AND E;


SYNTHESIZED_WIRE_43 <= SYNTHESIZED_WIRE_28 AND SYNTHESIZED_WIRE_29;


SYNTHESIZED_WIRE_33 <= SYNTHESIZED_WIRE_56 AND SYNTHESIZED_WIRE_59 AND SYNTHESIZED_WIRE_58;


SYNTHESIZED_WIRE_34 <= E AND F;


SYNTHESIZED_WIRE_42 <= SYNTHESIZED_WIRE_33 AND SYNTHESIZED_WIRE_34;


SYNTHESIZED_WIRE_38 <= SYNTHESIZED_WIRE_56 AND SYNTHESIZED_WIRE_59 AND D;


SYNTHESIZED_WIRE_39 <= SYNTHESIZED_WIRE_60 AND F;


SYNTHESIZED_WIRE_44 <= SYNTHESIZED_WIRE_38 AND SYNTHESIZED_WIRE_39;


SYNTHESIZED_WIRE_50 <= A AND SYNTHESIZED_WIRE_57 AND D;


SYNTHESIZED_WIRE_56 <= NOT(A);



SYNTHESIZED_WIRE_59 <= NOT(B);



SYNTHESIZED_WIRE_57 <= NOT(C);



SYNTHESIZED_WIRE_9 <= SYNTHESIZED_WIRE_41 OR SYNTHESIZED_WIRE_42 OR SYNTHESIZED_WIRE_43 OR SYNTHESIZED_WIRE_44 OR SYNTHESIZED_WIRE_45 OR SYNTHESIZED_WIRE_46 OR SYNTHESIZED_WIRE_47 OR SYNTHESIZED_WIRE_48;


SYNTHESIZED_WIRE_58 <= NOT(D);



SYNTHESIZED_WIRE_60 <= NOT(E);




SYNTHESIZED_WIRE_51 <= SYNTHESIZED_WIRE_60 AND F;


SYNTHESIZED_WIRE_48 <= SYNTHESIZED_WIRE_50 AND SYNTHESIZED_WIRE_51;


SYNTHESIZED_WIRE_53 <= B AND C AND D;


SYNTHESIZED_WIRE_54 <= SYNTHESIZED_WIRE_60 AND F;


SYNTHESIZED_WIRE_47 <= SYNTHESIZED_WIRE_53 AND SYNTHESIZED_WIRE_54;


SYNTHESIZED_WIRE_2 <= A AND SYNTHESIZED_WIRE_59 AND C;


SYNTHESIZED_WIRE_3 <= E AND F;


END bdf_type;

Project1/primeExtension/testbenchExtension.vhd
-- Rose Agyapong
-- Spring 2024
-- CS 232 Project1_Primer_Extension
-- Test file for the primerExtension

library ieee;
use ieee.std_logic_1164.all;

entity testbenchExtension is
end testbenchExtension;

architecture one of testbenchExtension is

  signal A, B, C, D, E, F, O: std_logic;

  component primeExtension
  port( 
    A :  IN  STD_LOGIC;
    B :  IN  STD_LOGIC;
	 C :  IN  STD_LOGIC;
	 D :  IN  STD_LOGIC;
	 E :  IN  STD_LOGIC;
	 F :  IN  STD_LOGIC;
    O :  OUT  STD_LOGIC
    );
  end component;

begin
F <= '0', '1' after 10 ns, '0' after 20 ns, '1' after 30 ns, '0' after 40 ns, '1' after 50 ns, '0' after 60 ns, '1' after 70 ns, '0' after 80 ns, '1' after 90 ns, '0' after 100 ns, '1' after 110 ns, '0' after 120 ns, '1' after 130 ns, '0' after 140 ns, '1' after 150 ns, '0' after 160 ns, '1' after 170 ns, '0' after 180 ns, '1' after 190 ns, '0' after 200 ns, '1' after 210 ns, '0' after 220 ns, '1' after 230 ns, '0' after 240 ns, '1' after 250 ns, '0' after 260 ns, '1' after 270 ns, '0' after 280 ns, '1' after 290 ns, '0' after 300 ns, '1' after 310 ns, '0' after 320 ns, '1' after 330 ns, '0' after 340 ns, '1' after 350 ns, '0' after 360 ns, '1' after 370 ns, '0' after 380 ns, '1' after 390 ns, '0' after 400 ns, '1' after 410 ns, '0' after 420 ns, '1' after 430 ns, '0' after 440 ns, '1' after 450 ns, '0' after 460 ns, '1' after 470 ns, '0' after 480 ns, '1' after 490 ns, '0' after 500 ns, '1' after 510 ns, '0' after 520 ns, '1' after 530 ns, '0' after 540 ns, '1' after 550 ns, '0' after 560 ns, '1' after 570 ns, '0' after 580 ns, '1' after 590 ns, '0' after 600 ns, '1' after 610 ns, '0' after 620 ns, '1' after 630 ns, '0' after 640 ns;
E <= '0', '1' after 20 ns, '0' after 40 ns, '1' after 60 ns, '0' after 80 ns, '1' after 100 ns, '0' after 120 ns, '1' after 140 ns, '0' after 160 ns, '1' after 180 ns, '0' after 200 ns, '1' after 220 ns, '0' after 240 ns, '1' after 260 ns, '0' after 280 ns, '1' after 300 ns, '0' after 320 ns, '1' after 340 ns, '0' after 360 ns, '1' after 380 ns, '0' after 400 ns, '1' after 420 ns, '0' after 440 ns, '1' after 460 ns, '0' after 480 ns, '1' after 500 ns, '0' after 520 ns, '1' after 540 ns, '0' after 560 ns, '1' after 580 ns, '0' after 600 ns, '1' after 620 ns, '0' after 640 ns;
D <= '0', '1' after 40 ns, '0' after 80 ns, '1' after 120 ns, '0' after 160 ns, '1' after 200 ns, '0' after 240 ns, '1' after 280 ns, '0' after 320 ns, '1' after 360 ns, '0' after 400 ns, '1' after 440 ns, '0' after 480 ns, '1' after 520 ns, '0' after 560 ns, '1' after 600 ns, '0' after 640 ns;
C <= '0', '1' after 80 ns, '0' after 160 ns, '1' after 240 ns, '0' after 320 ns, '1' after 400 ns, '0' after 480 ns, '1' after 560 ns, '0' after 640 ns;
B <= '0', '1' after 160 ns, '0' after 320 ns, '1' after 480 ns, '0' after 640 ns;
A <= '0', '1' after 320 ns, '0' after 640 ns;

T0: primeExtension port map(A, B, C, D, E, F, O);

end one;

Project1/primeExtension/testbenchExtension.vcd
$date
  Wed Feb 26 19:55:04 2025
$end
$version
  GHDL v0
$end
$timescale
  1 fs
$end
$scope module standard $end
$upscope $end
$scope module std_logic_1164 $end
$upscope $end
$scope module testbenchextension $end
$var reg 1 ! a $end
$var reg 1 " b $end
$var reg 1 # c $end
$var reg 1 $ d $end
$var reg 1 % e $end
$var reg 1 & f $end
$var reg 1 ' o $end
$scope module t0 $end
$var reg 1 ( a $end
$var reg 1 ) b $end
$var reg 1 * c $end
$var reg 1 + d $end
$var reg 1 , e $end
$var reg 1 - f $end
$var reg 1 . o $end
$var reg 1 / synthesized_wire_56 $end
$var reg 1 0 synthesized_wire_57 $end
$var reg 1 1 synthesized_wire_2 $end
$var reg 1 2 synthesized_wire_3 $end
$var reg 1 3 synthesized_wire_58 $end
$var reg 1 4 synthesized_wire_5 $end
$var reg 1 5 synthesized_wire_6 $end
$var reg 1 6 synthesized_wire_8 $end
$var reg 1 7 synthesized_wire_9 $end
$var reg 1 8 synthesized_wire_10 $end
$var reg 1 9 synthesized_wire_11 $end
$var reg 1 : synthesized_wire_59 $end
$var reg 1 ; synthesized_wire_14 $end
$var reg 1 < synthesized_wire_15 $end
$var reg 1 = synthesized_wire_16 $end
$var reg 1 > synthesized_wire_17 $end
$var reg 1 ? synthesized_wire_18 $end
$var reg 1 @ synthesized_wire_22 $end
$var reg 1 A synthesized_wire_23 $end
$var reg 1 B synthesized_wire_28 $end
$var reg 1 C synthesized_wire_29 $end
$var reg 1 D synthesized_wire_33 $end
$var reg 1 E synthesized_wire_34 $end
$var reg 1 F synthesized_wire_60 $end
$var reg 1 G synthesized_wire_38 $end
$var reg 1 H synthesized_wire_39 $end
$var reg 1 I synthesized_wire_41 $end
$var reg 1 J synthesized_wire_42 $end
$var reg 1 K synthesized_wire_43 $end
$var reg 1 L synthesized_wire_44 $end
$var reg 1 M synthesized_wire_45 $end
$var reg 1 N synthesized_wire_46 $end
$var reg 1 O synthesized_wire_47 $end
$var reg 1 P synthesized_wire_48 $end
$var reg 1 Q synthesized_wire_50 $end
$var reg 1 R synthesized_wire_51 $end
$var reg 1 S synthesized_wire_53 $end
$var reg 1 T synthesized_wire_54 $end
$upscope $end
$upscope $end
$enddefinitions $end
#0
0!
0"
0#
0$
0%
0&
0'
0(
0)
0*
0+
0,
0-
0.
1/
10
01
02
13
04
05
06
07
08
09
1:
0;
0<
0=
0>
0?
0@
0A
1B
0C
1D
0E
1F
0G
0H
0I
0J
0K
0L
0M
0N
0O
0P
0Q
0R
0S
0T
#10000000
1&
1-
1?
1A
1H
1R
1T
#20000000
1%
0&
1'
1,
0-
1.
17
0?
0A
1C
0F
0H
1K
0R
0T
#30000000
1&
1-
12
15
19
1?
1A
1E
1I
1J
#40000000
1$
0%
0&
0'
1+
0,
0-
0.
02
03
05
07
09
0?
0A
0C
0D
0E
1F
1G
0I
0J
0K
#50000000
1&
1'
1-
1.
17
1H
1L
1R
1T
#60000000
1%
0&
0'
1,
0-
0.
07
0F
0H
0L
0R
0T
#70000000
1&
1'
1-
1.
12
15
17
19
1E
1I
#80000000
1#
0$
0%
0&
0'
1*
0+
0,
0-
0.
00
02
13
05
07
09
0B
1D
0E
1F
0G
0I
#90000000
1&
1-
1?
1A
1H
1R
1T
#100000000
1%
0&
1,
0-
0?
0A
1C
0F
0H
0R
0T
#110000000
1&
1'
1-
1.
12
15
17
19
1?
1A
1E
1J
#120000000
1$
0%
0&
0'
1+
0,
0-
0.
02
03
05
07
09
0?
0A
0C
0D
0E
1F
1G
0J
#130000000
1&
1'
1-
1.
17
1H
1L
1R
1T
#140000000
1%
0&
0'
1,
0-
0.
07
0F
0H
0L
0R
0T
#150000000
1&
1-
12
15
19
1E
#160000000
1"
0#
0$
0%
0&
1)
0*
0+
0,
0-
10
02
13
05
09
0:
1@
0E
1F
0G
#170000000
1&
1'
1-
1.
17
1?
1A
1H
1N
1R
1T
#180000000
1%
0&
0'
1,
0-
0.
07
0?
0A
1C
0F
0H
0N
0R
0T
#190000000
1&
1'
1-
1.
12
15
17
19
1?
1A
1E
1I
1N
#200000000
1$
0%
0&
0'
1+
0,
0-
0.
02
03
05
07
18
09
0?
0A
0C
0E
1F
0I
0N
#210000000
1&
1-
1H
1R
1T
#220000000
1%
0&
1,
0-
0F
0H
0R
0T
#230000000
1&
1'
1-
1.
12
15
17
19
1E
1I
1M
#240000000
1#
0$
0%
0&
0'
1*
0+
0,
0-
0.
00
02
13
05
07
08
09
0@
0E
1F
0I
0M
#250000000
1&
1-
1?
1A
1H
1R
1T
#260000000
1%
0&
1,
0-
0?
0A
1C
0F
0H
0R
0T
#270000000
1&
1-
12
15
19
1?
1A
1E
#280000000
1$
0%
0&
1+
0,
0-
02
03
05
18
09
0?
0A
0C
0E
1F
1S
#290000000
1&
1'
1-
1.
17
1H
1O
1R
1T
#300000000
1%
0&
0'
1,
0-
0.
07
0F
0H
0O
0R
0T
#310000000
1&
1'
1-
1.
12
15
17
19
1E
1M
#320000000
1!
0"
0#
0$
0%
0&
0'
1(
0)
0*
0+
0,
0-
0.
0/
10
02
13
05
07
08
09
1:
0E
1F
0M
0S
#330000000
1&
1-
1?
1A
1H
1R
1T
#340000000
1%
0&
1,
0-
0?
0A
1C
0F
0H
0R
0T
#350000000
1&
1-
12
15
19
1?
1A
1E
#360000000
1$
0%
0&
1+
0,
0-
02
03
05
09
0?
0A
0C
0E
1F
1Q
#370000000
1&
1'
1-
1.
17
1H
1P
1R
1T
#380000000
1%
0&
0'
1,
0-
0.
07
0F
0H
0P
0R
0T
#390000000
1&
1-
12
15
19
1E
#400000000
1#
0$
0%
0&
1*
0+
0,
0-
00
11
02
13
14
05
09
1>
0E
1F
0Q
#410000000
1&
1'
1-
1.
16
1=
1?
1A
1H
1R
1T
#420000000
1%
0&
0'
1,
0-
0.
06
0=
0?
0A
1C
0F
0H
0R
0T
#430000000
1&
1'
1-
1.
12
15
16
19
1;
1<
1=
1?
1A
1E
#440000000
1$
0%
0&
0'
1+
0,
0-
0.
02
03
04
05
06
09
0;
0<
0=
0?
0A
0C
0E
1F
#450000000
1&
1-
1H
1R
1T
#460000000
1%
0&
1,
0-
0F
0H
0R
0T
#470000000
1&
1'
1-
1.
12
15
16
19
1;
1E
#480000000
1"
0#
0$
0%
0&
0'
1)
0*
0+
0,
0-
0.
10
01
02
13
05
06
09
0:
0;
0>
0E
1F
#490000000
1&
1-
1?
1A
1H
1R
1T
#500000000
1%
0&
1,
0-
0?
0A
1C
0F
0H
0R
0T
#510000000
1&
1-
12
15
19
1?
1A
1E
#520000000
1$
0%
0&
1+
0,
0-
02
03
05
09
0?
0A
0C
0E
1F
1Q
#530000000
1&
1'
1-
1.
17
1H
1P
1R
1T
#540000000
1%
0&
0'
1,
0-
0.
07
0F
0H
0P
0R
0T
#550000000
1&
1-
12
15
19
1E
#560000000
1#
0$
0%
0&
1*
0+
0,
0-
00
02
13
14
05
09
0E
1F
0Q
#570000000
1&
1-
1?
1A
1H
1R
1T
#580000000
1%
0&
1,
0-
0?
0A
1C
0F
0H
0R
0T
#590000000
1&
1'
1-
1.
12
15
16
19
1<
1?
1A
1E
#600000000
1$
0%
0&
0'
1+
0,
0-
0.
02
03
04
05
06
09
0<
0?
0A
0C
0E
1F
1S
#610000000
1&
1'
1-
1.
17
1H
1O
1R
1T
#620000000
1%
0&
0'
1,
0-
0.
07
0F
0H
0O
0R
0T
#630000000
1&
1-
12
15
19
1E
#640000000
0!
0"
0#
0$
0%
0&
0(
0)
0*
0+
0,
0-
1/
10
02
13
05
09
1:
1B
1D
0E
1F
0S
