Project1/prime/prime.vhd
-- Copyright (C) 1991-2013 Altera Corporation
-- Your use of Altera Corporation's design tools, logic functions 
-- and other software and tools, and its AMPP partner logic 
-- functions, and any output files from any of the foregoing 
-- (including device programming or simulation files), and any 
-- associated documentation or information are expressly subject 
-- to the terms and conditions of the Altera Program License 
-- Subscription Agreement, Altera MegaCore Function License 
-- Agreement, or other applicable license agreement, including, 
-- without limitation, that your use is for the sole purpose of 
-- programming logic devices manufactured by Altera and sold by 
-- Altera or its authorized distributors.  Please refer to the 
-- applicable agreement for further details.

-- PROGRAM		"Quartus II 32-bit"
-- VERSION		"Version 13.1.0 Build 162 10/23/2013 SJ Web Edition"
-- CREATED		"Fri Feb 21 21:54:35 2025"

LIBRARY ieee;
USE ieee.std_logic_1164.all; 

LIBRARY work;

ENTITY prime IS 
	PORT
	(
		A :  IN  STD_LOGIC;
		B :  IN  STD_LOGIC;
		C :  IN  STD_LOGIC;
		D :  IN  STD_LOGIC;
		F :  OUT  STD_LOGIC
	);
END prime;

ARCHITECTURE bdf_type OF prime IS 

SIGNAL	SYNTHESIZED_WIRE_0 :  STD_LOGIC;
SIGNAL	SYNTHESIZED_WIRE_1 :  STD_LOGIC;
SIGNAL	SYNTHESIZED_WIRE_2 :  STD_LOGIC;
SIGNAL	SYNTHESIZED_WIRE_3 :  STD_LOGIC;
SIGNAL	SYNTHESIZED_WIRE_4 :  STD_LOGIC;
SIGNAL	SYNTHESIZED_WIRE_5 :  STD_LOGIC;
SIGNAL	SYNTHESIZED_WIRE_6 :  STD_LOGIC;
SIGNAL	SYNTHESIZED_WIRE_7 :  STD_LOGIC;
SIGNAL	SYNTHESIZED_WIRE_8 :  STD_LOGIC;
SIGNAL	SYNTHESIZED_WIRE_9 :  STD_LOGIC;


BEGIN 



SYNTHESIZED_WIRE_5 <= NOT(A);



SYNTHESIZED_WIRE_6 <= B AND SYNTHESIZED_WIRE_0 AND D;


SYNTHESIZED_WIRE_0 <= NOT(C);



SYNTHESIZED_WIRE_7 <= SYNTHESIZED_WIRE_1 AND SYNTHESIZED_WIRE_2 AND C AND SYNTHESIZED_WIRE_3;


SYNTHESIZED_WIRE_8 <= A AND SYNTHESIZED_WIRE_4 AND C AND D;


SYNTHESIZED_WIRE_9 <= SYNTHESIZED_WIRE_5 AND C AND D;


SYNTHESIZED_WIRE_1 <= NOT(A);



SYNTHESIZED_WIRE_2 <= NOT(B);



SYNTHESIZED_WIRE_3 <= NOT(D);



SYNTHESIZED_WIRE_4 <= NOT(B);



F <= SYNTHESIZED_WIRE_6 OR SYNTHESIZED_WIRE_7 OR SYNTHESIZED_WIRE_8 OR SYNTHESIZED_WIRE_9;


END bdf_type;

Project1/prime/prime_testbench.vhd
-- Rose Frimpomaa Agyapong
-- Spring 2025
-- CS 232 Lab 1
-- Test file for the simple circuit in lab 1

library ieee;
use ieee.std_logic_1164.all;

entity prime_testbench is
end prime_testbench;

architecture one of prime_testbench is

  signal a, b, c, d, f: std_logic;

  component prime
  port( 
    A :  IN  STD_LOGIC;
    B :  IN  STD_LOGIC;
    C :  IN  STD_LOGIC;
    D :  IN  STD_LOGIC;
    F :  OUT  STD_LOGIC
    );
  end component;

begin

A <= '0', '1' after 200 ns;
B <= '0', '1' after 100 ns, '0' after 200 ns, '1' after 300 ns;
C <= '0', '1' after 50 ns, '0' after 100 ns, '1' after 150 ns, '0' after 200 ns, '1' after 250 ns, '0' after 300 ns, '1' after 350 ns;
D <= '0', '1' after 25 ns, '0' after 50 ns, '1' after 75 ns, '0' after 100 ns, '1' after 125 ns, '0' after 150 ns, '1' after 175 ns, '0' after 200 ns, '1' after 225 ns, '0' after 250 ns, '1' after 275 ns, '0' after 300 ns, '1' after 325 ns, '0' after 350 ns, '1' after 375 ns;

T0: prime port map(A, B, C, D, F);

end one;

Project1/prime/prime_testbench.vcd
$date
  Wed Feb 26 19:14:47 2025
$end
$version
  GHDL v0
$end
$timescale
  1 fs
$end
$scope module standard $end
$upscope $end
$scope module std_logic_1164 $end
$upscope $end
$scope module prime_testbench $end
$var reg 1 ! a $end
$var reg 1 " b $end
$var reg 1 # c $end
$var reg 1 $ d $end
$var reg 1 % f $end
$scope module t0 $end
$var reg 1 & a $end
$var reg 1 ' b $end
$var reg 1 ( c $end
$var reg 1 ) d $end
$var reg 1 * f $end
$var reg 1 + synthesized_wire_0 $end
$var reg 1 , synthesized_wire_1 $end
$var reg 1 - synthesized_wire_2 $end
$var reg 1 . synthesized_wire_3 $end
$var reg 1 / synthesized_wire_4 $end
$var reg 1 0 synthesized_wire_5 $end
$var reg 1 1 synthesized_wire_6 $end
$var reg 1 2 synthesized_wire_7 $end
$var reg 1 3 synthesized_wire_8 $end
$var reg 1 4 synthesized_wire_9 $end
$upscope $end
$upscope $end
$enddefinitions $end
#0
0!
0"
0#
0$
0%
0&
0'
0(
0)
0*
1+
1,
1-
1.
1/
10
01
02
03
04
#25000000
1$
1)
0.
#50000000
1#
0$
1%
1(
0)
1*
0+
1.
12
#75000000
1$
1)
0.
02
14
#100000000
1"
0#
0$
0%
1'
0(
0)
0*
1+
0-
1.
0/
04
#125000000
1$
1%
1)
1*
0.
11
#150000000
1#
0$
0%
1(
0)
0*
0+
1.
01
#175000000
1$
1%
1)
1*
0.
14
#200000000
1!
0"
0#
0$
0%
1&
0'
0(
0)
0*
1+
0,
1-
1.
1/
00
04
#225000000
1$
1)
0.
#250000000
1#
0$
1(
0)
0+
1.
#275000000
1$
1%
1)
1*
0.
13
#300000000
1"
0#
0$
0%
1'
0(
0)
0*
1+
0-
1.
0/
03
#325000000
1$
1%
1)
1*
0.
11
#350000000
1#
0$
0%
1(
0)
0*
0+
1.
01
#375000000
1$
1)
0.
